ttlinks/__init__.py
ttlinks/common/__init__.py
ttlinks/common/algorithm/__init__.py
ttlinks/common/algorithm/checksum.py
ttlinks/common/algorithm/trie.py
ttlinks/common/binary_utils/__init__.py
ttlinks/common/binary_utils/binary.py
ttlinks/common/binary_utils/binary_factory.py
ttlinks/common/design_template/__init__.py
ttlinks/common/design_template/cor.py
ttlinks/common/design_template/factory.py
ttlinks/common/tools/__init__.py
ttlinks/common/tools/converters.py
ttlinks/common/tools/network.py
ttlinks/common/tools/systems.py
ttlinks/files/__init__.py
ttlinks/files/file_classifiers.py
ttlinks/files/file_types.py
ttlinks/files/file_utils.py
ttlinks/ipservice/__init__.py
ttlinks/ipservice/ip_addr_type_classifiers.py
ttlinks/ipservice/ip_address.py
ttlinks/ipservice/ip_configs.py
ttlinks/ipservice/ip_converters.py
ttlinks/ipservice/ip_factory.py
ttlinks/ipservice/ip_format_standardizer.py
ttlinks/ipservice/ip_subnet_type_classifiers.py
ttlinks/ipservice/ip_type_classifiers.py
ttlinks/ipservice/ip_utils.py
ttlinks/ipservice/test.py
ttlinks/ipservice/wildcard_calculator.py
ttlinks/macservice/__init__.py
ttlinks/macservice/mac_address.py
ttlinks/macservice/mac_classifiers.py
ttlinks/macservice/mac_converters.py
ttlinks/macservice/mac_factory.py
ttlinks/macservice/mac_utils.py
ttlinks/macservice/oui_db_manager.py
ttlinks/macservice/oui_file_parsers.py
ttlinks/macservice/oui_utils.py
ttlinks/macservice/test.py
ttlinks/macservice/data/__init__.py
ttlinks/macservice/data/default_cid.json
ttlinks/macservice/data/default_iab.json
ttlinks/macservice/data/default_mal.json
ttlinks/macservice/data/default_mam.json
ttlinks/macservice/data/default_mas.json
ttlinks/macservice/oui_db/__init__.py
ttlinks/macservice/oui_db/database.py
ttlinks/macservice/oui_db/loaders.py
ttlinks/macservice/oui_db/searchers.py
ttlinks/macservice/oui_db/serializers.py
ttlinks/macservice/oui_db/updaters.py
ttlinks/macservice/resources/__init__.py
ttlinks/macservice/resources/default_cid.csv
ttlinks-0.3.9.dist-info/LICENSE.txt
ttlinks-0.3.9.dist-info/METADATA
ttlinks-0.3.9.dist-info/WHEEL
ttlinks-0.3.9.dist-info/top_level.txt
ttlinks-0.3.9.dist-info/RECORD
