Metadata-Version: 2.1
Name: ttlinks
Version: 0.3.9
Summary: TTLinks Network Service Packages
Home-page: https://github.com/tyt063144/TTLinks.git
Author: Yantao Tao
Author-email: tytccie@gmail.com
License: MIT
Keywords: network,ttlinks,networking,automation,ip,mac,python,wildcard,subnet,network automation
Classifier: Development Status :: 5 - Production/Stable
Classifier: Intended Audience :: Developers
Classifier: Intended Audience :: System Administrators
Classifier: Intended Audience :: End Users/Desktop
Classifier: Intended Audience :: Telecommunications Industry
Classifier: Operating System :: Unix
Classifier: Programming Language :: Python :: 3 :: Only
Classifier: Topic :: System :: Networking
License-File: LICENSE.txt
Requires-Dist: inflect
